_setuptools/__init__.py
notcallback/__init__.py
notcallback/_version.py
notcallback/async_.py
notcallback/base.py
notcallback/exceptions.py
notcallback/promise.py
notcallback/utils.py
notcallback-0.0.8.dist-info/LICENSE
notcallback-0.0.8.dist-info/METADATA
notcallback-0.0.8.dist-info/WHEEL
notcallback-0.0.8.dist-info/top_level.txt
notcallback-0.0.8.dist-info/RECORD
