Metadata-Version: 2.1
Name: notcallback
Version: 0.0.8
Summary: Promise-style interfaces for callback-based asynchronous libraries.
Home-page: https://github.com/monotony113/notcallback
Author: Tony Wu
Author-email: tony(dot)wu(at)nyu(dot)edu@inval.id
License: MIT
Keywords: promise async asyncio
Platform: UNKNOWN
Classifier: Development Status :: 3 - Alpha
Classifier: Intended Audience :: Developers
Classifier: License :: OSI Approved :: MIT License
Classifier: Programming Language :: Python :: 3 :: Only
Classifier: Programming Language :: Python :: 3.3
Classifier: Programming Language :: Python :: 3.4
Classifier: Programming Language :: Python :: 3.5
Classifier: Programming Language :: Python :: 3.6
Classifier: Programming Language :: Python :: 3.7
Classifier: Programming Language :: Python :: 3.8
Classifier: Topic :: Software Development :: Libraries
Classifier: Framework :: AsyncIO
Requires-Python: >=3.6
